pidme.py
setup.py
pidme.egg-info/PKG-INFO
pidme.egg-info/SOURCES.txt
pidme.egg-info/dependency_links.txt
pidme.egg-info/top_level.txt