Metadata-Version: 1.0
Name: pidme
Version: 1.0
Summary: Pidfile creation and cleanup
Home-page: http://github.com/ccollins/pidme
Author: Chuck Collins
Author-email: chuck.collins@gmail.com
License: MIT
Keywords: pid pidfile python
Platform: UNKNOWN
